colorific/__init__.py
colorific/config.py
colorific/palette.py
colorific/script.py
colorific-0.3.dist-info/DESCRIPTION.rst
colorific-0.3.dist-info/entry_points.txt
colorific-0.3.dist-info/METADATA
colorific-0.3.dist-info/metadata.json
colorific-0.3.dist-info/RECORD
colorific-0.3.dist-info/top_level.txt
colorific-0.3.dist-info/WHEEL
