Metadata-Version: 1.1
Name: colorific
Version: 0.3
Summary: Automatic color palette detection
Home-page: http://github.com/99designs/colorific
Author: Lars Yencken
Author-email: lars@yencken.org
License: ISC
Platform: UNKNOWN
Classifier: Development Status :: 4 - Beta
Classifier: Intended Audience :: Developers
Classifier: Intended Audience :: Science/Research
Classifier: License :: OSI Approved :: ISC License (ISCL)
Classifier: Natural Language :: English
Classifier: Programming Language :: Python :: 2
Classifier: Programming Language :: Python :: 2.7
Classifier: Programming Language :: Python :: 3
Classifier: Programming Language :: Python :: 3.3
Classifier: Programming Language :: Python :: 3.4
